zengl_imgui.py
zengl_imgui-1.0.0.dist-info/METADATA
zengl_imgui-1.0.0.dist-info/WHEEL
zengl_imgui-1.0.0.dist-info/top_level.txt
zengl_imgui-1.0.0.dist-info/RECORD
