Metadata-Version: 2.1
Name: zengl-imgui
Version: 1.0.0
Requires-Dist: zengl
Requires-Dist: imgui
